hbmep/__init__.py
hbmep/__main__.py
hbmep/dataset.py
hbmep/functional.py
hbmep/infer.py
hbmep/plotter.py
hbmep/smooth_functional.py
hbmep/model/__init__.py
hbmep/model/base_model.py
hbmep/model/non_hierarchical.py
hbmep/model/standard.py
hbmep/util/__init__.py
hbmep/util/site.py
hbmep/util/util.py
hbmep-0.7.0.dist-info/licenses/LICENSE
hbmep-0.7.0.dist-info/METADATA
hbmep-0.7.0.dist-info/WHEEL
hbmep-0.7.0.dist-info/top_level.txt
hbmep-0.7.0.dist-info/RECORD
